gawseed/__init__.py
gawseed/threatfeed/__init__.py
gawseed/threatfeed/config.py
gawseed/threatfeed/loader.py
gawseed/threatfeed/main.py
gawseed/threatfeed/pkl2report.py
gawseed/threatfeed/datasources/__init__.py
gawseed/threatfeed/datasources/bro.py
gawseed/threatfeed/datasources/druid.py
gawseed/threatfeed/datasources/fsdb.py
gawseed/threatfeed/datasources/json.py
gawseed/threatfeed/datasources/kafka.py
gawseed/threatfeed/enrichments/__init__.py
gawseed/threatfeed/enrichments/connectionCounter.py
gawseed/threatfeed/enrichments/connectionGrapher.py
gawseed/threatfeed/enrichments/connsummarizer.py
gawseed/threatfeed/enrichments/datasource.py
gawseed/threatfeed/enrichments/dnssummarizer.py
gawseed/threatfeed/enrichments/priorityTotal.py
gawseed/threatfeed/enrichments/similarIPsGraph.py
gawseed/threatfeed/enrichments/sorter.py
gawseed/threatfeed/enrichments/summarizer.py
gawseed/threatfeed/events/__init__.py
gawseed/threatfeed/events/archiver.py
gawseed/threatfeed/events/dumper.py
gawseed/threatfeed/events/extrainfo.py
gawseed/threatfeed/events/misp.py
gawseed/threatfeed/events/multisummarizer.py
gawseed/threatfeed/events/printer.py
gawseed/threatfeed/events/reporter.py
gawseed/threatfeed/events/summarizer.py
gawseed/threatfeed/feeds/__init__.py
gawseed/threatfeed/feeds/fsdb.py
gawseed/threatfeed/feeds/kafka.py
gawseed/threatfeed/search/__init__.py
gawseed/threatfeed/search/dns.py
gawseed/threatfeed/search/http.py
gawseed/threatfeed/search/ip.py
gawseed/threatfeed/search/iprange.py
gawseed/threatfeed/search/keys.py
gawseed/threatfeed/search/parallel.py
gawseed/threatfeed/search/re.py
gawseed/threatfeed/search/ssh.py
gawseed/threatfeed/tools/__init__.py
gawseed/threatfeed/tools/main.py
gawseed/threatfeed/tools/pkl2misp.py
gawseed/threatfeed/tools/pkl2report.py
gawseed/threatfeed/tools/pklcompare.py
gawseed_threat_feed_tools-1.1.15.dist-info/LICENSE
gawseed_threat_feed_tools-1.1.15.dist-info/METADATA
gawseed_threat_feed_tools-1.1.15.dist-info/WHEEL
gawseed_threat_feed_tools-1.1.15.dist-info/entry_points.txt
gawseed_threat_feed_tools-1.1.15.dist-info/top_level.txt
gawseed_threat_feed_tools-1.1.15.dist-info/RECORD
