Metadata-Version: 2.1
Name: gawseed-threat-feed-tools
Version: 1.1.15
Summary: Tools to search network data logs for threat feed data
Home-page: https://github.com/gawseed/threat-feed-tools
Author: Wes Hardaker and USC/ISI
Author-email: opensource@hardakers.net
License: UNKNOWN
Platform: UNKNOWN
Classifier: Programming Language :: Python :: 3
Classifier: Operating System :: OS Independent
Requires-Python: >=3.0
License-File: LICENSE
Requires-Dist: pyfsdb (>=0.9.92)
Requires-Dist: kafka-python
Requires-Dist: python-dateutil
Requires-Dist: jinja2
Requires-Dist: pyyaml (>5)
Requires-Dist: msgpack
Requires-Dist: lz4
Requires-Dist: graphviz
Requires-Dist: dnssplitter
Requires-Dist: urllib3
